[
  {
    "comment": "Here we define the name of our workflow",
    "content": "name: Hello world"
  },
  {
    "comment": "Here we define how the workflow should be executed",
    "content": "on:\n  push:\n    branches:\n      - main"
  },
  {
    "comment": "And here we define the steps that the workflow should execute",
    "content": "jobs:\n  hello-world:"
  },
  {
    "comment": "Now we define the runner that the job will run on",
    "content": "    runs-on: ubuntu-latest\n    steps:\n      - name: Hello world\n        run: echo \"Hello world\"\n      - name: Test"
  },
  {
    "comment": "We can use multiple lines",
    "content": "        run: |\n          ls -all\n          echo \"Hello world\""
  }
]